thorlabs_elliptec/__init__.py
thorlabs_elliptec-1.2.0.dist-info/LICENSE
thorlabs_elliptec-1.2.0.dist-info/METADATA
thorlabs_elliptec-1.2.0.dist-info/WHEEL
thorlabs_elliptec-1.2.0.dist-info/top_level.txt
thorlabs_elliptec-1.2.0.dist-info/RECORD
