Metadata-Version: 2.1
Name: thorlabs_elliptec
Version: 1.2.0
Summary: Interface to ThorLabs Elliptec piezo-driven motion stages and mounts.
Home-page: https://gitlab.com/ptapping/thorlabs-elliptec
Author: Patrick Tapping
Author-email: mail@patricktapping.com
Project-URL: Documentation, https://thorlabs-elliptec.readthedocs.io/
Project-URL: Source, https://gitlab.com/ptapping/thorlabs-elliptec
Project-URL: Tracker, https://gitlab.com/ptapping/thorlabs-elliptec/-/issues
Classifier: Programming Language :: Python :: 3
Classifier: License :: OSI Approved :: GNU General Public License v3 or later (GPLv3+)
Classifier: Operating System :: OS Independent
Requires-Python: >=3.7
License-File: LICENSE
Requires-Dist: pyserial
